<?xml version="1.0" encoding="utf-8"?>
<NationCollection xmlns:xsd="http://www.w3.org/2001/XMLSchema" xmlns:xsi="http://www.w3.org/2001/XMLSchema-instance">

  <!-- 

	Here's an example nation. 
	To add new nations you can make your own XML file in this folder or just add new ones to these files.
	In either case they will be loaded when you open the program.
  
    <Nation>
	
      <Name>(EA) My Cool Nation</Name>        
      /// This is the name that appears in the program. 
	  
      <ID>69</ID>                             
      /// The ID of the nation. A value of -1 makes the program use the nation as a generic nation.
	  
      <WaterPercentage>0.2</WaterPercentage>  
      /// How much water does the nation get in their allotted provinces? 
	    /// In a standard map layout, every nation gets a square of 16 provinces.
			/// This water percentage ignores the provinces used as the nation's capring or cap.
			/// For example, let's give a nation a capring size of 5 and a water percentage of 0.2
			/// 6 provinces are used for the cap/capring, so 20% of the remaining 10 provinces becomes water.
	  
      <Age>EARLY</Age>                        
      /// Which age does this nation appear in? 
	    /// Possible options are: 
			/// ALL, EARLY, MIDDLE, LATE

      <HasCaveEntranceInCapRing>true</HasCaveEntranceInCapRing>                        
      /// Does the nation have a cave entrance in one of their capring provinces? (Only for Dom6) 
	  
      <CapRingSize>5</CapRingSize>            
      /// How many provinces are in the nation's capring? This value can be between 4 and 8 inclusive.
	    /// Typically a value of 5 or 6 is best.
	  
      <CapTerrain>SMALLPROV FOREST</CapTerrain> 
      /// What terrain flag does the nation's capital get?
	    /// Terrain flags can be combined together. For example, SMALLPROV FOREST gives you a small forest.
			/// Certain combinations should not be done since they do not exist in the game. For example, SEA SWAMP.
		  /// The DEEPSEA flag always has to be combined with SEA in order to work properly.
			/// Possible flags are: 
			/// PLAINS, HIGHLAND, SWAMP, WASTE, FOREST, FARM, MOUNTAINS, SEA, DEEPSEA, SMALLPROV, LARGEPROV, WARMER, COLDER
	  
      <TerrainData>FOREST</TerrainData>       
      <TerrainData>FOREST</TerrainData>       
      <TerrainData>PLAINS</TerrainData>       
      <TerrainData>SWAMP</TerrainData>         
      /// TerrainData is applied to the capring provinces in random order.
      /// Make sure there are not more TerrainData entries than the size of the capring.
      /// If you have less TerrainData entries than the capring size, the remaining provinces are assigned random terrain.
      /// In this example nation, only 4 capring provinces are given specific terrain. The 5th province will be random.

    </Nation>
  
  -->

  <Nation>
    <Name>(EA) Arcoscephale</Name>
    <ID>5</ID>
    <WaterPercentage>0</WaterPercentage>
    <Age>EARLY</Age>
    <CapRingSize>5</CapRingSize>
    <CapTerrain>MOUNTAINS</CapTerrain>
    <TerrainData>FOREST</TerrainData>
    <TerrainData>FOREST</TerrainData>
    <TerrainData>PLAINS</TerrainData>
    <TerrainData>PLAINS</TerrainData>
  </Nation>
  <Nation>
    <Name>(EA) Mekone</Name>
    <ID>6</ID>
    <WaterPercentage>0</WaterPercentage>
    <Age>EARLY</Age>
    <CapRingSize>5</CapRingSize>
    <CapTerrain>MOUNTAINS</CapTerrain>
    <TerrainData>PLAINS</TerrainData>
    <TerrainData>PLAINS</TerrainData>
    <TerrainData>FOREST</TerrainData>
  </Nation>
  <Nation>
    <Name>(EA) Pangaea</Name>
    <ID>7</ID>
    <WaterPercentage>0</WaterPercentage>
    <Age>EARLY</Age>
    <CapRingSize>5</CapRingSize>
    <CapTerrain>FOREST</CapTerrain>
    <TerrainData>SMALLPROV FOREST</TerrainData>
    <TerrainData>SMALLPROV FOREST</TerrainData>
    <TerrainData>HIGHLAND</TerrainData>
  </Nation>
  <Nation>
    <Name>(EA) Ermor</Name>
    <ID>8</ID>
    <WaterPercentage>0</WaterPercentage>
    <Age>EARLY</Age>
    <CapRingSize>5</CapRingSize>
    <CapTerrain>PLAINS</CapTerrain>
    <TerrainData>PLAINS</TerrainData>
    <TerrainData>PLAINS</TerrainData>
    <TerrainData>FOREST</TerrainData>
  </Nation>
  <Nation>
    <Name>(EA) Sauromatia</Name>
    <ID>9</ID>
    <WaterPercentage>0</WaterPercentage>
    <Age>EARLY</Age>
    <CapRingSize>5</CapRingSize>
    <CapTerrain>PLAINS</CapTerrain>
    <TerrainData>FOREST</TerrainData>
    <TerrainData>FOREST</TerrainData>
    <TerrainData>PLAINS</TerrainData>
  </Nation>
  <Nation>
    <Name>(EA) Fomoria</Name>
    <ID>10</ID>
    <WaterPercentage>0.2</WaterPercentage>
    <Age>EARLY</Age>
    <CapRingSize>6</CapRingSize>
    <CapTerrain>PLAINS</CapTerrain>
    <TerrainData>FOREST</TerrainData>
    <TerrainData>PLAINS</TerrainData>
    <TerrainData>PLAINS</TerrainData>
	  <TerrainData>SEA</TerrainData>
  </Nation>
  <Nation>
    <Name>(EA) Tir Na N'og</Name>
    <ID>11</ID>
    <WaterPercentage>0</WaterPercentage>
    <Age>EARLY</Age>
    <CapRingSize>5</CapRingSize>
    <CapTerrain>PLAINS</CapTerrain>
    <TerrainData>PLAINS</TerrainData>
    <TerrainData>FOREST</TerrainData>
    <TerrainData>FOREST</TerrainData>
  </Nation>
  <Nation>
    <Name>(EA) Marverni</Name>
    <ID>12</ID>
    <WaterPercentage>0</WaterPercentage>
    <Age>EARLY</Age>
    <CapRingSize>5</CapRingSize>
    <CapTerrain>PLAINS</CapTerrain>
    <TerrainData>PLAINS</TerrainData>
    <TerrainData>FOREST</TerrainData>
    <TerrainData>FOREST</TerrainData>
  </Nation>
  <Nation>
    <Name>(EA) Ulm</Name>
    <ID>13</ID>
    <WaterPercentage>0</WaterPercentage>
    <Age>EARLY</Age>
    <CapRingSize>5</CapRingSize>
    <CapTerrain>FOREST</CapTerrain>
    <TerrainData>FOREST</TerrainData>
    <TerrainData>FOREST</TerrainData>
    <TerrainData>PLAINS</TerrainData>
  </Nation>
  <Nation>
    <Name>(EA) Agartha</Name>
    <ID>15</ID>
    <WaterPercentage>0.1</WaterPercentage>
    <StartsUnderground>true</StartsUnderground>
    <HasCaveEntranceInCapRing>true</HasCaveEntranceInCapRing>
    <Age>EARLY</Age>
    <CapRingSize>4</CapRingSize>
    <CapTerrain>PLAINS</CapTerrain>
    <TerrainData>SWAMP</TerrainData>
    <TerrainData>PLAINS</TerrainData>
    <TerrainData>PLAINS</TerrainData>
  </Nation>
  <Nation>
    <Name>(EA) Abysia</Name>
    <ID>16</ID>
    <WaterPercentage>0</WaterPercentage>
    <HasCaveEntranceInCapRing>true</HasCaveEntranceInCapRing>
    <Age>EARLY</Age>
    <CapRingSize>5</CapRingSize>
    <CapTerrain>WASTE</CapTerrain>
    <TerrainData>FOREST</TerrainData>
    <TerrainData>PLAINS</TerrainData>
    <TerrainData>PLAINS</TerrainData>
  </Nation>
  <Nation>
    <Name>(EA) Abysia (Cave)</Name>
    <ID>16</ID>
    <WaterPercentage>0</WaterPercentage>
    <StartsUnderground>true</StartsUnderground>
    <HasCaveEntranceInCapRing>true</HasCaveEntranceInCapRing>
    <Age>EARLY</Age>
    <CapRingSize>4</CapRingSize>
    <CapTerrain>PLAINS</CapTerrain>
    <TerrainData>HIGHLAND</TerrainData>
    <TerrainData>PLAINS</TerrainData>
    <TerrainData>PLAINS</TerrainData>
  </Nation>
  <Nation>
    <Name>(EA) Hinnom</Name>
    <ID>17</ID>
    <WaterPercentage>0</WaterPercentage>
    <Age>EARLY</Age>
    <CapRingSize>5</CapRingSize>
    <CapTerrain>WASTE</CapTerrain>
    <TerrainData>FOREST</TerrainData>
    <TerrainData>PLAINS</TerrainData>
    <TerrainData>PLAINS</TerrainData>
  </Nation>
  <Nation>
    <Name>(EA) Ubar</Name>
    <ID>18</ID>
    <WaterPercentage>0</WaterPercentage>
    <Age>EARLY</Age>
    <CapRingSize>5</CapRingSize>
    <CapTerrain>WASTE</CapTerrain>
    <TerrainData>LARGEPROV WASTE</TerrainData>
    <TerrainData>PLAINS</TerrainData>
    <TerrainData>PLAINS</TerrainData>
	  <TerrainData>FOREST</TerrainData>
  </Nation>
  <Nation>
    <Name>(EA) Ur</Name>
    <ID>19</ID>
    <WaterPercentage>0.1</WaterPercentage>
    <Age>EARLY</Age>
    <CapRingSize>5</CapRingSize>
    <CapTerrain>PLAINS</CapTerrain>
    <TerrainData>FOREST</TerrainData>
    <TerrainData>PLAINS</TerrainData>
    <TerrainData>PLAINS</TerrainData>
    <TerrainData>LARGEPROV SWAMP</TerrainData>
  </Nation>
  <Nation>
    <Name>(EA) Kailasa</Name>
    <ID>20</ID>
    <WaterPercentage>0</WaterPercentage>
    <Age>EARLY</Age>
    <CapRingSize>5</CapRingSize>
    <CapTerrain>MOUNTAINS</CapTerrain>
    <TerrainData>FOREST</TerrainData>
    <TerrainData>FOREST</TerrainData>
    <TerrainData>PLAINS</TerrainData>
  </Nation>
  <Nation>
    <Name>(EA) Lanka</Name>
    <ID>21</ID>
    <WaterPercentage>0</WaterPercentage>
    <Age>EARLY</Age>
    <CapRingSize>5</CapRingSize>
    <CapTerrain>FOREST</CapTerrain>
    <TerrainData>FOREST</TerrainData>
    <TerrainData>FOREST</TerrainData>
    <TerrainData>PLAINS</TerrainData>
  </Nation>
  <Nation>
    <Name>(EA) T'ien Chi</Name>
    <ID>22</ID>
    <WaterPercentage>0</WaterPercentage>
    <Age>EARLY</Age>
    <CapRingSize>5</CapRingSize>
    <CapTerrain>PLAINS</CapTerrain>
    <TerrainData>FOREST</TerrainData>
    <TerrainData>FOREST</TerrainData>
    <TerrainData>PLAINS</TerrainData>
  </Nation>
  <Nation>
    <Name>(EA) Yomi</Name>
    <ID>23</ID>
    <WaterPercentage>0</WaterPercentage>
    <Age>EARLY</Age>
    <CapRingSize>6</CapRingSize>
    <CapTerrain>MOUNTAINS</CapTerrain>
    <TerrainData>FOREST</TerrainData>
    <TerrainData>FOREST</TerrainData>
    <TerrainData>HIGHLAND</TerrainData>
    <TerrainData>SMALLPROV</TerrainData>
  </Nation>
  <Nation>
    <Name>(EA) Caelum</Name>
    <ID>24</ID>
    <WaterPercentage>0</WaterPercentage>
    <Age>EARLY</Age>
    <CapRingSize>5</CapRingSize>
    <CapTerrain>MOUNTAINS</CapTerrain>
    <TerrainData>FOREST</TerrainData>
    <TerrainData>FOREST</TerrainData>
    <TerrainData>PLAINS</TerrainData>
  </Nation>
  <Nation>
    <Name>(EA) Mictlan</Name>
    <ID>25</ID>
    <WaterPercentage>0</WaterPercentage>
    <Age>EARLY</Age>
    <CapRingSize>5</CapRingSize>
    <CapTerrain>FOREST</CapTerrain>
    <TerrainData>FOREST</TerrainData>
    <TerrainData>FOREST</TerrainData>
    <TerrainData>PLAINS</TerrainData>
  </Nation>
  <Nation>
    <Name>(EA) Xibalba</Name>
    <ID>26</ID>
    <WaterPercentage>0</WaterPercentage>
    <StartsUnderground>true</StartsUnderground>
    <HasCaveEntranceInCapRing>true</HasCaveEntranceInCapRing>
    <Age>EARLY</Age>
    <CapRingSize>4</CapRingSize>
    <CapTerrain>SWAMP</CapTerrain>
    <TerrainData>FOREST</TerrainData>
    <TerrainData>PLAINS</TerrainData>
    <TerrainData>PLAINS</TerrainData>
  </Nation>
  <Nation>
    <Name>(EA) C'tis</Name>
    <ID>27</ID>
    <WaterPercentage>0</WaterPercentage>
    <Age>EARLY</Age>
    <CapRingSize>5</CapRingSize>
    <CapTerrain>SWAMP</CapTerrain>
    <TerrainData>FOREST</TerrainData>
    <TerrainData>FOREST</TerrainData>
    <TerrainData>PLAINS</TerrainData>
  </Nation>
  <Nation>
    <Name>(EA) Machaka</Name>
    <ID>28</ID>
    <WaterPercentage>0</WaterPercentage>
    <Age>EARLY</Age>
    <CapRingSize>5</CapRingSize>
    <CapTerrain>PLAINS</CapTerrain>
    <TerrainData>FOREST</TerrainData>
    <TerrainData>FOREST</TerrainData>
    <TerrainData>PLAINS</TerrainData>
  </Nation>
  <Nation>
    <Name>(EA) Berytos</Name>
    <ID>29</ID>
    <WaterPercentage>0.2</WaterPercentage>
    <Age>EARLY</Age>
    <CapRingSize>6</CapRingSize>
    <CapTerrain>PLAINS</CapTerrain>
    <TerrainData>FOREST</TerrainData>
    <TerrainData>FOREST</TerrainData>
    <TerrainData>PLAINS</TerrainData>
	  <TerrainData>SEA</TerrainData>
  </Nation>
  <Nation>
    <Name>(EA) Vanheim</Name>
    <ID>30</ID>
    <WaterPercentage>0.1</WaterPercentage>
    <Age>EARLY</Age>
    <CapRingSize>5</CapRingSize>
    <CapTerrain>MOUNTAINS</CapTerrain>
    <TerrainData>PLAINS</TerrainData>
    <TerrainData>FOREST</TerrainData>
    <TerrainData>HIGHLAND</TerrainData>
  </Nation>
  <Nation>
    <Name>(EA) Helheim</Name>
    <ID>31</ID>
    <WaterPercentage>0</WaterPercentage>
    <Age>EARLY</Age>
    <CapRingSize>5</CapRingSize>
    <CapTerrain>HIGHLAND</CapTerrain>
    <TerrainData>PLAINS</TerrainData>
    <TerrainData>FOREST</TerrainData>
    <TerrainData>HIGHLAND</TerrainData>
  </Nation>
  <Nation>
    <Name>(EA) Rus</Name>
    <ID>32</ID>
    <WaterPercentage>0</WaterPercentage>
    <Age>EARLY</Age>
    <CapRingSize>5</CapRingSize>
    <CapTerrain>PLAINS</CapTerrain>
    <TerrainData>FOREST</TerrainData>
    <TerrainData>FOREST</TerrainData>
    <TerrainData>PLAINS</TerrainData>
  </Nation>
  <Nation>
    <Name>(EA) Niefelheim</Name>
    <ID>33</ID>
    <WaterPercentage>0</WaterPercentage>
    <Age>EARLY</Age>
    <CapRingSize>5</CapRingSize>
    <CapTerrain>PLAINS</CapTerrain>
    <TerrainData>FOREST</TerrainData>
    <TerrainData>FOREST</TerrainData>
    <TerrainData>PLAINS</TerrainData>
  </Nation>
  <Nation>
    <Name>(EA) Pelagia</Name>
    <ID>40</ID>
    <WaterPercentage>0.4</WaterPercentage>
    <Age>EARLY</Age>
    <CapRingSize>5</CapRingSize>
    <CapTerrain>SEA</CapTerrain>
    <TerrainData>SEA DEEPSEA</TerrainData>
    <TerrainData>SEA FOREST</TerrainData>
    <TerrainData>SEA</TerrainData>
    <TerrainData>SEA</TerrainData>
    <TerrainData>SEA</TerrainData>
  </Nation>
  <Nation>
    <Name>(EA) Oceania</Name>
    <ID>41</ID>
    <WaterPercentage>0.4</WaterPercentage>
    <Age>EARLY</Age>
    <CapRingSize>5</CapRingSize>
    <CapTerrain>SEA FOREST</CapTerrain>
    <TerrainData>SEA FOREST</TerrainData>
    <TerrainData>SEA FOREST</TerrainData>
    <TerrainData>SEA</TerrainData>
    <TerrainData>SEA</TerrainData>
    <TerrainData>SEA</TerrainData>
  </Nation>
  <Nation>
    <Name>(EA) Therodos</Name>
    <ID>42</ID>
    <WaterPercentage>0.4</WaterPercentage>
    <Age>EARLY</Age>
    <CapRingSize>5</CapRingSize>
    <CapTerrain>SEA HIGHLAND</CapTerrain>
    <TerrainData>SEA HIGHLAND</TerrainData>
    <TerrainData>SEA FOREST</TerrainData>
    <TerrainData>SEA</TerrainData>
    <TerrainData>SEA</TerrainData>
    <TerrainData>SEA</TerrainData>
  </Nation>
  <Nation>
    <Name>(EA) Atlantis</Name>
    <ID>43</ID>
    <WaterPercentage>0.4</WaterPercentage>
    <HasCaveEntranceInCapRing>true</HasCaveEntranceInCapRing>
    <Age>EARLY</Age>
    <CapRingSize>5</CapRingSize>
    <CapTerrain>SEA DEEPSEA</CapTerrain>
    <TerrainData>SEA DEEPSEA</TerrainData>
    <TerrainData>SEA DEEPSEA</TerrainData>
    <TerrainData>SEA FOREST</TerrainData>
    <TerrainData>SEA</TerrainData>
    <TerrainData>SEA</TerrainData>
  </Nation>
  <Nation>
    <Name>(EA) R'lyeh</Name>
    <ID>44</ID>
    <WaterPercentage>0.4</WaterPercentage>
    <Age>EARLY</Age>
    <CapRingSize>5</CapRingSize>
    <CapTerrain>SEA DEEPSEA</CapTerrain>
    <TerrainData>SEA DEEPSEA</TerrainData>
    <TerrainData>SEA FOREST</TerrainData>
    <TerrainData>SEA</TerrainData>
    <TerrainData>SEA</TerrainData>
    <TerrainData>SEA</TerrainData>
  </Nation>
  <Nation>
    <Name>(MA) Arcoscephale</Name>
    <ID>50</ID>
    <WaterPercentage>0</WaterPercentage>
    <Age>MIDDLE</Age>
    <CapRingSize>5</CapRingSize>
    <CapTerrain>MOUNTAINS</CapTerrain>
    <TerrainData>FOREST</TerrainData>
    <TerrainData>FOREST</TerrainData>
    <TerrainData>PLAINS</TerrainData>
  </Nation>
  <Nation>
    <Name>(MA) Phlegra</Name>
    <ID>51</ID>
    <WaterPercentage>0</WaterPercentage>
    <Age>MIDDLE</Age>
    <CapRingSize>5</CapRingSize>
    <CapTerrain>MOUNTAINS</CapTerrain>
    <TerrainData>FOREST</TerrainData>
    <TerrainData>FOREST</TerrainData>
    <TerrainData>PLAINS</TerrainData>
  </Nation>
  <Nation>
    <Name>(MA) Pangaea</Name>
    <ID>52</ID>
    <WaterPercentage>0</WaterPercentage>
    <Age>MIDDLE</Age>
    <CapRingSize>5</CapRingSize>
    <CapTerrain>FOREST</CapTerrain>
    <TerrainData>SMALLPROV FOREST</TerrainData>
    <TerrainData>FOREST</TerrainData>
    <TerrainData>PLAINS</TerrainData>
  </Nation>
  <Nation>
    <Name>(MA) Asphodel</Name>
    <ID>53</ID>
    <WaterPercentage>0</WaterPercentage>
    <Age>MIDDLE</Age>
    <CapRingSize>5</CapRingSize>
    <CapTerrain>FOREST</CapTerrain>
    <TerrainData>FOREST</TerrainData>
    <TerrainData>FOREST</TerrainData>
    <TerrainData>PLAINS</TerrainData>
  </Nation>
  <Nation>
    <Name>(MA) Ermor</Name>
    <ID>54</ID>
    <WaterPercentage>0</WaterPercentage>
    <Age>MIDDLE</Age>
    <CapRingSize>5</CapRingSize>
    <CapTerrain>PLAINS</CapTerrain>
    <TerrainData>PLAINS</TerrainData>
    <TerrainData>PLAINS</TerrainData>
    <TerrainData>LARGEPROV WASTE</TerrainData>
  </Nation>
  <Nation>
    <Name>(MA) Sceleria</Name>
    <ID>55</ID>
    <WaterPercentage>0</WaterPercentage>
    <Age>MIDDLE</Age>
    <CapRingSize>5</CapRingSize>
    <CapTerrain>PLAINS</CapTerrain>
    <TerrainData>PLAINS</TerrainData>
    <TerrainData>PLAINS</TerrainData>
    <TerrainData>FOREST</TerrainData>
  </Nation>
  <Nation>
    <Name>(MA) Pythium</Name>
    <ID>56</ID>
    <WaterPercentage>0</WaterPercentage>
    <Age>MIDDLE</Age>
    <CapRingSize>5</CapRingSize>
    <CapTerrain>PLAINS</CapTerrain>
    <TerrainData>PLAINS</TerrainData>
    <TerrainData>PLAINS</TerrainData>
    <TerrainData>FOREST</TerrainData>
  </Nation>
  <Nation>
    <Name>(MA) Man</Name>
    <ID>57</ID>
    <WaterPercentage>0</WaterPercentage>
    <Age>MIDDLE</Age>
    <CapRingSize>5</CapRingSize>
    <CapTerrain>PLAINS</CapTerrain>
    <TerrainData>FOREST</TerrainData>
    <TerrainData>FOREST</TerrainData>
    <TerrainData>PLAINS</TerrainData>
  </Nation>
  <Nation>
    <Name>(MA) Eriu</Name>
    <ID>58</ID>
    <WaterPercentage>0</WaterPercentage>
    <Age>MIDDLE</Age>
    <CapRingSize>5</CapRingSize>
    <CapTerrain>PLAINS</CapTerrain>
    <TerrainData>PLAINS</TerrainData>
    <TerrainData>FOREST</TerrainData>
    <TerrainData>FOREST</TerrainData>
  </Nation>
  <Nation>
    <Name>(MA) Agartha</Name>
    <ID>59</ID>
    <WaterPercentage>0.1</WaterPercentage>
    <StartsUnderground>true</StartsUnderground>
    <HasCaveEntranceInCapRing>true</HasCaveEntranceInCapRing>
    <Age>MIDDLE</Age>
    <CapRingSize>4</CapRingSize>
    <CapTerrain>PLAINS</CapTerrain>
    <TerrainData>PLAINS</TerrainData>
    <TerrainData>PLAINS</TerrainData>
    <TerrainData>FOREST</TerrainData>
  </Nation>
  <Nation>
    <Name>(MA) Ulm</Name>
    <ID>60</ID>
    <WaterPercentage>0</WaterPercentage>
    <Age>MIDDLE</Age>
    <CapRingSize>5</CapRingSize>
    <CapTerrain>PLAINS</CapTerrain>
    <TerrainData>FOREST</TerrainData>
    <TerrainData>PLAINS</TerrainData>
    <TerrainData>PLAINS</TerrainData>
  </Nation>
  <Nation>
    <Name>(MA) Marignon</Name>
    <ID>61</ID>
    <WaterPercentage>0</WaterPercentage>
    <Age>MIDDLE</Age>
    <CapRingSize>5</CapRingSize>
    <CapTerrain>PLAINS</CapTerrain>
    <TerrainData>FOREST</TerrainData>
    <TerrainData>PLAINS</TerrainData>
    <TerrainData>PLAINS</TerrainData>
  </Nation>
  <Nation>
    <Name>(MA) Abysia</Name>
    <ID>63</ID>
    <WaterPercentage>0</WaterPercentage>
    <HasCaveEntranceInCapRing>true</HasCaveEntranceInCapRing>
    <Age>MIDDLE</Age>
    <CapRingSize>5</CapRingSize>
    <CapTerrain>WASTE</CapTerrain>
    <TerrainData>FOREST</TerrainData>
    <TerrainData>PLAINS</TerrainData>
    <TerrainData>PLAINS</TerrainData>
  </Nation>
  <Nation>
    <Name>(MA) Abysia (Cave)</Name>
    <ID>63</ID>
    <WaterPercentage>0</WaterPercentage>
    <StartsUnderground>true</StartsUnderground>
    <HasCaveEntranceInCapRing>true</HasCaveEntranceInCapRing>
    <Age>MIDDLE</Age>
    <CapRingSize>4</CapRingSize>
    <CapTerrain>PLAINS</CapTerrain>
    <TerrainData>HIGHLAND</TerrainData>
    <TerrainData>PLAINS</TerrainData>
    <TerrainData>PLAINS</TerrainData>
  </Nation>
  <Nation>
    <Name>(MA) Ashdod</Name>
    <ID>64</ID>
    <WaterPercentage>0</WaterPercentage>
    <Age>MIDDLE</Age>
    <CapRingSize>5</CapRingSize>
    <CapTerrain>WASTE</CapTerrain>
    <TerrainData>LARGEPROV WASTE</TerrainData>
    <TerrainData>FOREST</TerrainData>
    <TerrainData>FOREST</TerrainData>
    <TerrainData>PLAINS</TerrainData>
  </Nation>
  <Nation>
    <Name>(MA) Na'Ba</Name>
    <ID>65</ID>
    <WaterPercentage>0</WaterPercentage>
    <Age>MIDDLE</Age>
    <CapRingSize>5</CapRingSize>
    <CapTerrain>WASTE</CapTerrain>
    <TerrainData>LARGEPROV WASTE</TerrainData>
    <TerrainData>FOREST</TerrainData>
    <TerrainData>FOREST</TerrainData>
    <TerrainData>PLAINS</TerrainData>
  </Nation>
  <Nation>
    <Name>(MA) Uruk</Name>
    <ID>66</ID>
    <WaterPercentage>0.1</WaterPercentage>
    <Age>MIDDLE</Age>
    <CapRingSize>5</CapRingSize>
    <CapTerrain>PLAINS</CapTerrain>
    <TerrainData>FOREST</TerrainData>
    <TerrainData>FOREST</TerrainData>
    <TerrainData>PLAINS</TerrainData>
  </Nation>
  <Nation>
    <Name>(MA) Ind</Name>
    <ID>67</ID>
    <WaterPercentage>0</WaterPercentage>
    <Age>MIDDLE</Age>
    <CapRingSize>5</CapRingSize>
    <CapTerrain>PLAINS</CapTerrain>
    <TerrainData>FOREST</TerrainData>
    <TerrainData>FOREST</TerrainData>
    <TerrainData>PLAINS</TerrainData>
  </Nation>
  <Nation>
    <Name>(MA) Bandar Log</Name>
    <ID>68</ID>
    <WaterPercentage>0</WaterPercentage>
    <Age>MIDDLE</Age>
    <CapRingSize>5</CapRingSize>
    <CapTerrain>FOREST</CapTerrain>
    <TerrainData>FOREST</TerrainData>
    <TerrainData>FOREST</TerrainData>
    <TerrainData>PLAINS</TerrainData>
  </Nation>
  <Nation>
    <Name>(MA) T'ien Chi</Name>
    <ID>69</ID>
    <WaterPercentage>0</WaterPercentage>
    <Age>MIDDLE</Age>
    <CapRingSize>5</CapRingSize>
    <CapTerrain>PLAINS</CapTerrain>
    <TerrainData>FOREST</TerrainData>
    <TerrainData>FOREST</TerrainData>
    <TerrainData>PLAINS</TerrainData>
  </Nation>
  <Nation>
    <Name>(MA) Shinuyama</Name>
    <ID>70</ID>
    <WaterPercentage>0</WaterPercentage>
    <Age>MIDDLE</Age>
    <CapRingSize>5</CapRingSize>
    <CapTerrain>MOUNTAINS</CapTerrain>
    <TerrainData>FOREST</TerrainData>
    <TerrainData>PLAINS</TerrainData>
    <TerrainData>PLAINS</TerrainData>
  </Nation>
  <Nation>
    <Name>(MA) Caelum</Name>
    <ID>71</ID>
    <WaterPercentage>0</WaterPercentage>
    <Age>MIDDLE</Age>
    <CapRingSize>5</CapRingSize>
    <CapTerrain>MOUNTAINS</CapTerrain>
    <TerrainData>FOREST</TerrainData>
    <TerrainData>FOREST</TerrainData>
    <TerrainData>PLAINS</TerrainData>
  </Nation>
  <Nation>
    <Name>(MA) Nazca</Name>
    <ID>72</ID>
    <WaterPercentage>0</WaterPercentage>
    <Age>MIDDLE</Age>
    <CapRingSize>5</CapRingSize>
    <CapTerrain>MOUNTAINS</CapTerrain>
    <TerrainData>LARGEPROV WASTE</TerrainData>
    <TerrainData>FOREST</TerrainData>
    <TerrainData>HIGHLAND</TerrainData>
    <TerrainData>PLAINS</TerrainData>
  </Nation>
  <Nation>
    <Name>(MA) Mictlan</Name>
    <ID>73</ID>
    <WaterPercentage>0</WaterPercentage>
    <Age>MIDDLE</Age>
    <CapRingSize>5</CapRingSize>
    <CapTerrain>FOREST</CapTerrain>
    <TerrainData>FOREST</TerrainData>
    <TerrainData>FOREST</TerrainData>
    <TerrainData>PLAINS</TerrainData>
  </Nation>
  <Nation>
    <Name>(MA) Xibalba</Name>
    <ID>74</ID>
    <WaterPercentage>0.1</WaterPercentage>
    <StartsUnderground>true</StartsUnderground>
    <HasCaveEntranceInCapRing>true</HasCaveEntranceInCapRing>
    <Age>MIDDLE</Age>
    <CapRingSize>4</CapRingSize>
    <CapTerrain>SWAMP</CapTerrain>
    <TerrainData>FOREST</TerrainData>
    <TerrainData>PLAINS</TerrainData>
    <TerrainData>PLAINS</TerrainData>
  </Nation>
  <Nation>
    <Name>(MA) C'tis</Name>
    <ID>75</ID>
    <WaterPercentage>0</WaterPercentage>
    <Age>MIDDLE</Age>
    <CapRingSize>5</CapRingSize>
    <CapTerrain>SWAMP</CapTerrain>
    <TerrainData>LARGEPROV SWAMP</TerrainData>
    <TerrainData>PLAINS</TerrainData>
    <TerrainData>FOREST</TerrainData>
    <TerrainData>FOREST</TerrainData>
  </Nation>
  <Nation>
    <Name>(MA) Machaka</Name>
    <ID>76</ID>
    <WaterPercentage>0</WaterPercentage>
    <Age>MIDDLE</Age>
    <CapRingSize>5</CapRingSize>
    <CapTerrain>FOREST</CapTerrain>
    <TerrainData>FOREST</TerrainData>
    <TerrainData>FOREST</TerrainData>
    <TerrainData>PLAINS</TerrainData>
  </Nation>
  <Nation>
    <Name>(MA) Phaeacia (Land)</Name>
    <ID>77</ID>
    <WaterPercentage>0.3</WaterPercentage>
    <Age>MIDDLE</Age>
    <CapRingSize>6</CapRingSize>
    <CapTerrain>PLAINS</CapTerrain>
    <TerrainData>PLAINS</TerrainData>
    <TerrainData>FOREST</TerrainData>
    <TerrainData>FOREST</TerrainData>
    <TerrainData>SEA</TerrainData>
    <TerrainData>SEA</TerrainData>
  </Nation>
  <Nation>
    <Name>(MA) Phaeacia (Island)</Name>
    <ID>77</ID>
    <WaterPercentage>0.2</WaterPercentage>
    <Age>MIDDLE</Age>
    <CapRingSize>5</CapRingSize>
    <CapTerrain>PLAINS</CapTerrain>
    <TerrainData>SEA HIGHLAND</TerrainData>
    <TerrainData>SEA</TerrainData>
    <TerrainData>SEA</TerrainData>
    <TerrainData>SEA</TerrainData>
    <TerrainData>SEA</TerrainData>
  </Nation>
  <Nation>
    <Name>(MA) Vanheim</Name>
    <ID>78</ID>
    <WaterPercentage>0.1</WaterPercentage>
    <Age>MIDDLE</Age>
    <CapRingSize>5</CapRingSize>
    <CapTerrain>HIGHLAND</CapTerrain>
    <TerrainData>FOREST</TerrainData>
    <TerrainData>PLAINS</TerrainData>
    <TerrainData>HIGHLAND</TerrainData>
  </Nation>
  <Nation>
    <Name>(MA) Vanarus</Name>
    <ID>79</ID>
    <WaterPercentage>0</WaterPercentage>
    <Age>MIDDLE</Age>
    <CapRingSize>5</CapRingSize>
    <CapTerrain>FOREST</CapTerrain>
    <TerrainData>FOREST</TerrainData>
    <TerrainData>FOREST</TerrainData>
    <TerrainData>PLAINS</TerrainData>
  </Nation>
  <Nation>
    <Name>(MA) Jotunheim</Name>
    <ID>80</ID>
    <WaterPercentage>0</WaterPercentage>
    <Age>MIDDLE</Age>
    <CapRingSize>5</CapRingSize>
    <CapTerrain>FOREST</CapTerrain>
    <TerrainData>FOREST</TerrainData>
    <TerrainData>PLAINS</TerrainData>
    <TerrainData>PLAINS</TerrainData>
  </Nation>
  <Nation>
    <Name>(MA) Ys</Name>
    <ID>85</ID>
    <WaterPercentage>0.3</WaterPercentage>
    <Age>MIDDLE</Age>
    <CapRingSize>5</CapRingSize>
    <CapTerrain>SEA</CapTerrain>
    <TerrainData>SEA FOREST</TerrainData>
    <TerrainData>SEA FOREST</TerrainData>
    <TerrainData>SEA</TerrainData>
    <TerrainData>SEA</TerrainData>
    <TerrainData>SEA</TerrainData>
  </Nation>
  <Nation>
    <Name>(MA) Pelagia</Name>
    <ID>86</ID>
    <WaterPercentage>0.4</WaterPercentage>
    <Age>MIDDLE</Age>
    <CapRingSize>5</CapRingSize>
    <CapTerrain>SEA</CapTerrain>
    <TerrainData>SEA FOREST</TerrainData>
    <TerrainData>SEA DEEPSEA</TerrainData>
    <TerrainData>SEA</TerrainData>
    <TerrainData>SEA</TerrainData>
    <TerrainData>SEA</TerrainData>
  </Nation>
  <Nation>
    <Name>(MA) Oceania</Name>
    <ID>87</ID>
    <WaterPercentage>0.4</WaterPercentage>
    <Age>MIDDLE</Age>
    <CapRingSize>5</CapRingSize>
    <CapTerrain>SEA FOREST</CapTerrain>
    <TerrainData>SEA FOREST</TerrainData>
    <TerrainData>SEA FOREST</TerrainData>
    <TerrainData>SEA HIGHLAND</TerrainData>
    <TerrainData>SEA</TerrainData>
    <TerrainData>SEA</TerrainData>
  </Nation>
  <Nation>
    <Name>(MA) Atlantis</Name>
    <ID>88</ID>
    <WaterPercentage>0.4</WaterPercentage>
    <HasCaveEntranceInCapRing>true</HasCaveEntranceInCapRing>
    <Age>MIDDLE</Age>
    <CapRingSize>5</CapRingSize>
    <CapTerrain>SEA DEEPSEA</CapTerrain>
    <TerrainData>SEA DEEPSEA</TerrainData>
    <TerrainData>SEA DEEPSEA</TerrainData>
    <TerrainData>SEA FOREST</TerrainData>
    <TerrainData>SEA</TerrainData>
    <TerrainData>SEA</TerrainData>
  </Nation>
  <Nation>
    <Name>(MA) R'lyeh</Name>
    <ID>89</ID>
    <WaterPercentage>0.4</WaterPercentage>
    <Age>MIDDLE</Age>
    <CapRingSize>5</CapRingSize>
    <CapTerrain>SEA DEEPSEA</CapTerrain>
    <TerrainData>SEA DEEPSEA</TerrainData>
    <TerrainData>SEA FOREST</TerrainData>
    <TerrainData>SEA</TerrainData>
    <TerrainData>SEA</TerrainData>
    <TerrainData>SEA</TerrainData>
  </Nation>
  <Nation>
    <Name>(LA) Arcoscephale</Name>
    <ID>95</ID>
    <WaterPercentage>0</WaterPercentage>
    <Age>LATE</Age>
    <CapRingSize>5</CapRingSize>
    <CapTerrain>MOUNTAINS</CapTerrain>
    <TerrainData>PLAINS</TerrainData>
    <TerrainData>FOREST</TerrainData>
    <TerrainData>FOREST</TerrainData>
  </Nation>
  <Nation>
    <Name>(LA) Phlegra</Name>
    <ID>96</ID>
    <WaterPercentage>0</WaterPercentage>
    <Age>LATE</Age>
    <CapRingSize>5</CapRingSize>
    <CapTerrain>MOUNTAINS</CapTerrain>
    <TerrainData>PLAINS</TerrainData>
    <TerrainData>PLAINS</TerrainData>
    <TerrainData>FOREST</TerrainData>
  </Nation>
  <Nation>
    <Name>(LA) Pangaea</Name>
    <ID>97</ID>
    <WaterPercentage>0</WaterPercentage>
    <Age>LATE</Age>
    <CapRingSize>5</CapRingSize>
    <CapTerrain>FOREST</CapTerrain>
    <TerrainData>FOREST</TerrainData>
    <TerrainData>FOREST</TerrainData>
    <TerrainData>PLAINS</TerrainData>
  </Nation>
  <Nation>
    <Name>(LA) Pythium</Name>
    <ID>98</ID>
    <WaterPercentage>0</WaterPercentage>
    <Age>LATE</Age>
    <CapRingSize>5</CapRingSize>
    <CapTerrain>PLAINS</CapTerrain>
    <TerrainData>PLAINS</TerrainData>
    <TerrainData>FOREST</TerrainData>
    <TerrainData>FOREST</TerrainData>
  </Nation>
  <Nation>
    <Name>(LA) Lemuria</Name>
    <ID>99</ID>
    <WaterPercentage>0</WaterPercentage>
    <Age>LATE</Age>
    <CapRingSize>5</CapRingSize>
    <CapTerrain>PLAINS</CapTerrain>
    <TerrainData>PLAINS</TerrainData>
    <TerrainData>PLAINS</TerrainData>
    <TerrainData>LARGEPROV WASTE</TerrainData>
  </Nation>
  <Nation>
    <Name>(LA) Man</Name>
    <ID>100</ID>
    <WaterPercentage>0</WaterPercentage>
    <Age>LATE</Age>
    <CapRingSize>5</CapRingSize>
    <CapTerrain>FOREST</CapTerrain>
    <TerrainData>FOREST</TerrainData>
    <TerrainData>FOREST</TerrainData>
    <TerrainData>PLAINS</TerrainData>
  </Nation>
  <Nation>
    <Name>(LA) Ulm</Name>
    <ID>101</ID>
    <WaterPercentage>0</WaterPercentage>
    <Age>LATE</Age>
    <CapRingSize>5</CapRingSize>
    <CapTerrain>PLAINS</CapTerrain>
    <TerrainData>FOREST</TerrainData>
    <TerrainData>PLAINS</TerrainData>
    <TerrainData>PLAINS</TerrainData>
  </Nation>
  <Nation>
    <Name>(LA) Agartha</Name>
    <ID>102</ID>
    <WaterPercentage>0</WaterPercentage>
    <StartsUnderground>true</StartsUnderground>
    <HasCaveEntranceInCapRing>true</HasCaveEntranceInCapRing>
    <Age>LATE</Age>
    <CapRingSize>4</CapRingSize>
    <CapTerrain>PLAINS</CapTerrain>
    <TerrainData>FOREST</TerrainData>
    <TerrainData>PLAINS</TerrainData>
    <TerrainData>PLAINS</TerrainData>
  </Nation>
  <Nation>
    <Name>(LA) Marignon</Name>
    <ID>103</ID>
    <WaterPercentage>0.2</WaterPercentage>
    <Age>LATE</Age>
    <CapRingSize>6</CapRingSize>
    <CapTerrain>PLAINS</CapTerrain>
    <TerrainData>PLAINS</TerrainData>
    <TerrainData>PLAINS</TerrainData>
    <TerrainData>FOREST</TerrainData>
    <TerrainData>SEA</TerrainData>
  </Nation>
  <Nation>
    <Name>(LA) Abysia</Name>
    <ID>104</ID>
    <WaterPercentage>0</WaterPercentage>
    <HasCaveEntranceInCapRing>true</HasCaveEntranceInCapRing>
    <Age>LATE</Age>
    <CapRingSize>5</CapRingSize>
    <CapTerrain>WASTE</CapTerrain>
    <TerrainData>FOREST</TerrainData>
    <TerrainData>PLAINS</TerrainData>
    <TerrainData>PLAINS</TerrainData>
  </Nation>
  <Nation>
    <Name>(LA) Abysia (Cave)</Name>
    <ID>104</ID>
    <StartsUnderground>true</StartsUnderground>
    <WaterPercentage>0</WaterPercentage>
    <HasCaveEntranceInCapRing>true</HasCaveEntranceInCapRing>
    <Age>LATE</Age>
    <CapRingSize>4</CapRingSize>
    <CapTerrain>PLAINS</CapTerrain>
    <TerrainData>HIGHLAND</TerrainData>
    <TerrainData>PLAINS</TerrainData>
    <TerrainData>PLAINS</TerrainData>
  </Nation>
  <Nation>
    <Name>(LA) Ragha</Name>
    <ID>105</ID>
    <WaterPercentage>0</WaterPercentage>
    <Age>LATE</Age>
    <CapRingSize>5</CapRingSize>
    <CapTerrain>PLAINS</CapTerrain>
    <TerrainData>FOREST</TerrainData>
    <TerrainData>FOREST</TerrainData>
    <TerrainData>PLAINS</TerrainData>
  </Nation>
  <Nation>
    <Name>(LA) Caelum</Name>
    <ID>106</ID>
    <WaterPercentage>0</WaterPercentage>
    <Age>LATE</Age>
    <CapRingSize>5</CapRingSize>
    <CapTerrain>MOUNTAINS</CapTerrain>
    <TerrainData>FOREST</TerrainData>
    <TerrainData>PLAINS</TerrainData>
    <TerrainData>PLAINS</TerrainData>
  </Nation>
  <Nation>
    <Name>(LA) Gath</Name>
    <ID>107</ID>
    <WaterPercentage>0</WaterPercentage>
    <Age>LATE</Age>
    <CapRingSize>5</CapRingSize>
    <CapTerrain>WASTE</CapTerrain>
    <TerrainData>PLAINS</TerrainData>
    <TerrainData>PLAINS</TerrainData>
    <TerrainData>FOREST</TerrainData>
  </Nation>
  <Nation>
    <Name>(LA) Patala</Name>
    <ID>108</ID>
    <WaterPercentage>0</WaterPercentage>
    <HasCaveEntranceInCapRing>true</HasCaveEntranceInCapRing>
    <Age>LATE</Age>
    <CapRingSize>5</CapRingSize>
    <CapTerrain>SWAMP</CapTerrain>
    <TerrainData>FOREST</TerrainData>
    <TerrainData>PLAINS</TerrainData>
    <TerrainData>PLAINS</TerrainData>
  </Nation>
  <Nation>
    <Name>(LA) T'ien Chi</Name>
    <ID>109</ID>
    <WaterPercentage>0</WaterPercentage>
    <Age>LATE</Age>
    <CapRingSize>5</CapRingSize>
    <CapTerrain>PLAINS</CapTerrain>
    <TerrainData>FOREST</TerrainData>
    <TerrainData>FOREST</TerrainData>
    <TerrainData>PLAINS</TerrainData>
  </Nation>
  <Nation>
    <Name>(LA) Jomon</Name>
    <ID>110</ID>
    <WaterPercentage>0.3</WaterPercentage>
    <Age>LATE</Age>
    <CapRingSize>5</CapRingSize>
    <CapTerrain>MOUNTAINS</CapTerrain>
    <TerrainData>FOREST</TerrainData>
    <TerrainData>FOREST</TerrainData>
    <TerrainData>PLAINS</TerrainData>
  </Nation>
  <Nation>
    <Name>(LA) Mictlan</Name>
    <ID>111</ID>
    <WaterPercentage>0.1</WaterPercentage>
    <Age>LATE</Age>
    <CapRingSize>5</CapRingSize>
    <CapTerrain>FOREST</CapTerrain>
    <TerrainData>FOREST</TerrainData>
    <TerrainData>FOREST</TerrainData>
    <TerrainData>PLAINS</TerrainData>
  </Nation>
  <Nation>
    <Name>(LA) Xibalba</Name>
    <ID>112</ID>
    <WaterPercentage>0.1</WaterPercentage>
    <StartsUnderground>true</StartsUnderground>
    <HasCaveEntranceInCapRing>true</HasCaveEntranceInCapRing>
    <Age>LATE</Age>
    <CapRingSize>4</CapRingSize>
    <CapTerrain>SWAMP</CapTerrain>
    <TerrainData>FOREST</TerrainData>
    <TerrainData>PLAINS</TerrainData>
    <TerrainData>PLAINS</TerrainData>
  </Nation>
  <Nation>
    <Name>(LA) C'tis</Name>
    <ID>113</ID>
    <WaterPercentage>0</WaterPercentage>
    <Age>LATE</Age>
    <CapRingSize>5</CapRingSize>
    <CapTerrain>WASTE</CapTerrain>
    <TerrainData>FOREST</TerrainData>
    <TerrainData>FOREST</TerrainData>
    <TerrainData>PLAINS</TerrainData>
  </Nation>
  <Nation>
    <Name>(LA) Midgard</Name>
    <ID>115</ID>
    <WaterPercentage>0.1</WaterPercentage>
    <Age>LATE</Age>
    <CapRingSize>5</CapRingSize>
    <CapTerrain>HIGHLAND</CapTerrain>
    <TerrainData>FOREST</TerrainData>
    <TerrainData>PLAINS</TerrainData>
    <TerrainData>HIGHLAND</TerrainData>
  </Nation>
  <Nation>
    <Name>(LA) Bogarus</Name>
    <ID>116</ID>
    <WaterPercentage>0</WaterPercentage>
    <Age>LATE</Age>
    <CapRingSize>5</CapRingSize>
    <CapTerrain>PLAINS</CapTerrain>
    <TerrainData>FOREST</TerrainData>
    <TerrainData>PLAINS</TerrainData>
    <TerrainData>PLAINS</TerrainData>
  </Nation>
  <Nation>
    <Name>(LA) Utgard</Name>
    <ID>117</ID>
    <WaterPercentage>0</WaterPercentage>
    <Age>LATE</Age>
    <CapRingSize>5</CapRingSize>
    <CapTerrain>FOREST</CapTerrain>
    <TerrainData>FOREST</TerrainData>
    <TerrainData>PLAINS</TerrainData>
    <TerrainData>PLAINS</TerrainData>
  </Nation>
  <Nation>
    <Name>(LA) Vaettiheim</Name>
    <ID>118</ID>
    <WaterPercentage>0</WaterPercentage>
    <Age>LATE</Age>
    <CapRingSize>5</CapRingSize>
    <CapTerrain>FOREST</CapTerrain>
    <TerrainData>PLAINS</TerrainData>
    <TerrainData>FOREST</TerrainData>
    <TerrainData>FOREST</TerrainData>
  </Nation>
  <Nation>
    <Name>(LA) Erytheia</Name>
    <ID>125</ID>
    <WaterPercentage>0.5</WaterPercentage>
    <Age>LATE</Age>
    <CapRingSize>5</CapRingSize>
    <CapTerrain>PLAINS</CapTerrain>
    <TerrainData>FOREST</TerrainData>
    <TerrainData>PLAINS</TerrainData>
    <TerrainData>PLAINS</TerrainData>
    <TerrainData>SEA</TerrainData>
  </Nation>
  <Nation>
    <Name>(LA) Atlantis</Name>
    <ID>126</ID>
    <WaterPercentage>0.5</WaterPercentage>
    <Age>LATE</Age>
    <CapRingSize>5</CapRingSize>
    <CapTerrain>PLAINS</CapTerrain>
    <TerrainData>FOREST</TerrainData>
    <TerrainData>FOREST</TerrainData>
    <TerrainData>PLAINS</TerrainData>
    <TerrainData>SEA</TerrainData>
  </Nation>
  <Nation>
    <Name>(LA) R'lyeh</Name>
    <ID>127</ID>
    <WaterPercentage>0.4</WaterPercentage>
    <Age>LATE</Age>
    <CapRingSize>5</CapRingSize>
    <CapTerrain>SEA DEEPSEA</CapTerrain>
    <TerrainData>SEA DEEPSEA</TerrainData>
    <TerrainData>SEA FOREST</TerrainData>
    <TerrainData>SEA</TerrainData>
    <TerrainData>SEA</TerrainData>
    <TerrainData>SEA</TerrainData>
  </Nation>
</NationCollection>